portal_tool/__init__.py
portal_tool/__main__.py
portal_tool/framework/framework_manager.py
portal_tool/framework/git_manager.py
portal_tool/installer/__init__.py
portal_tool/installer/configurator_factory.py
portal_tool/installer/configurators/__init__.py
portal_tool/installer/configurators/configurator.py
portal_tool/installer/configurators/linux_configurator.py
portal_tool/installer/configurators/mac_configurator.py
portal_tool/installer/configurators/windows_configurator.py
portal_tool/installer/installer.py
portal_tool/installer/repo/build_models.py
portal_tool/installer/repo/repo_maker.py
portal_tool/models.py
portal_tool/registry/registry_update.py
portal_tool/runner.py
portal_tool/singleton.py
portal_tool/templates/repo/bootstrap/cookiecutter.json
portal_tool/templates/repo/bootstrap/{{ cookiecutter.project_slug }}/.clang-format
portal_tool/templates/repo/bootstrap/{{ cookiecutter.project_slug }}/.gitignore
portal_tool/templates/repo/bootstrap/{{ cookiecutter.project_slug }}/CMakeLists.txt
portal_tool/templates/repo/bootstrap/{{ cookiecutter.project_slug }}/cmake/overlay-triplets/x64-windows.cmake
portal_tool/templates/repo/bootstrap/{{ cookiecutter.project_slug }}/cmake/overload-compiler.cmake
portal_tool/templates/repo/bootstrap/{{ cookiecutter.project_slug }}/config/.gitkeep
portal_tool/templates/repo/bootstrap/{{ cookiecutter.project_slug }}/resources/.gitkeep
portal_tool/templates/repo/bootstrap/{{ cookiecutter.project_slug }}/settings.json
portal_tool/templates/repo/bootstrap/{{ cookiecutter.project_slug }}/source/main.cpp
portal_tool/templates/repo/bootstrap/{{ cookiecutter.project_slug }}/vcpkg.json
portal_tool/templates/vcpkg/portfile.cmake-features.j2
portal_tool/templates/vcpkg/portfile.cmake.j2
portal_tool/templates/vcpkg/usage.j2
portal_tool/tool.py
portal_tool-0.2.2.dist-info/licenses/LICENSE
portal_tool-0.2.2.dist-info/WHEEL
portal_tool-0.2.2.dist-info/entry_points.txt
portal_tool-0.2.2.dist-info/METADATA
portal_tool-0.2.2.dist-info/RECORD
