Metadata-Version: 2.4
Name: portal_tool
Version: 0.2.2
Summary: Assortment of tools for the Portal project
Author: Jonatan Nevo
Author-email: Jonatan Nevo <jonatannevo-git@proton.me>
License-File: LICENSE
Requires-Dist: appdirs>=1.4.4
Requires-Dist: cookiecutter>=2.6.0
Requires-Dist: jinja2>=3.1.6,<4
Requires-Dist: pathlib>=1.0.1
Requires-Dist: pydantic>=2.11.4,<3
Requires-Dist: pydantic-settings>=2.12.0
Requires-Dist: requests>=2.32.5
Requires-Dist: textual>=6.6.0
Requires-Dist: tqdm>=4.67.1
Requires-Dist: typer>=0.15.3,<0.16
Requires-Python: >=3.12, <3.15
